common/__init__.py
common/extract/__init__.py
common/extract/extraction.py
common/load/__init__.py
common/load/base_loader.py
common/transform/__init__.py
common/transform/transformation.py
common/utils/__init__.py
common/utils/utils.py
common_etl-0.0.1.dist-info/METADATA
common_etl-0.0.1.dist-info/WHEEL
common_etl-0.0.1.dist-info/top_level.txt
common_etl-0.0.1.dist-info/RECORD
